<?xml version="1.0" encoding="utf-8"?>
<odoo>
    <data noupdate="1">
        <!-- SLA Policies for IT Request -->
        <record id="sla_issue_standard" model="it.sla.policy">
            <field name="name">IT Request - Standard (มาตรฐาน)</field>
            <field name="category">issue</field>
            <field name="sla_level">standard</field>
            <field name="response_time_hours">8</field>
            <field name="resolve_time_hours">72</field>
        </record>
        
        <record id="sla_issue_important" model="it.sla.policy">
            <field name="name">IT Request - Important (สำคัญ)</field>
            <field name="category">issue</field>
            <field name="sla_level">important</field>
            <field name="response_time_hours">4</field>
            <field name="resolve_time_hours">24</field>
        </record>
        
        <record id="sla_issue_urgent" model="it.sla.policy">
            <field name="name">IT Request - Urgent (เร่งด่วน)</field>
            <field name="category">issue</field>
            <field name="sla_level">urgent</field>
            <field name="response_time_hours">2</field>
            <field name="resolve_time_hours">8</field>
        </record>
        
        <record id="sla_issue_critical" model="it.sla.policy">
            <field name="name">IT Request - Critical (วิกฤต)</field>
            <field name="category">issue</field>
            <field name="sla_level">critical</field>
            <field name="response_time_hours">0.5</field>
            <field name="resolve_time_hours">4</field>
        </record>
        
        <!-- SLA Policies for Access Request -->
        <record id="sla_access_standard" model="it.sla.policy">
            <field name="name">Access - Standard (มาตรฐาน)</field>
            <field name="category">access</field>
            <field name="sla_level">standard</field>
            <field name="response_time_hours">24</field>
            <field name="resolve_time_hours">120</field>
        </record>
        
        <record id="sla_access_important" model="it.sla.policy">
            <field name="name">Access - Important (สำคัญ)</field>
            <field name="category">access</field>
            <field name="sla_level">important</field>
            <field name="response_time_hours">8</field>
            <field name="resolve_time_hours">48</field>
        </record>
        
        <record id="sla_access_urgent" model="it.sla.policy">
            <field name="name">Access - Urgent (เร่งด่วน)</field>
            <field name="category">access</field>
            <field name="sla_level">urgent</field>
            <field name="response_time_hours">4</field>
            <field name="resolve_time_hours">24</field>
        </record>
        
        <record id="sla_access_critical" model="it.sla.policy">
            <field name="name">Access - Critical (วิกฤต)</field>
            <field name="category">access</field>
            <field name="sla_level">critical</field>
            <field name="response_time_hours">1</field>
            <field name="resolve_time_hours">8</field>
        </record>
        
        <!-- SLA Policies for Purchase Request -->
        <record id="sla_purchase_standard" model="it.sla.policy">
            <field name="name">Purchase - Standard (มาตรฐาน)</field>
            <field name="category">purchase</field>
            <field name="sla_level">standard</field>
            <field name="response_time_hours">24</field>
            <field name="resolve_time_hours">240</field>
        </record>
        
        <record id="sla_purchase_important" model="it.sla.policy">
            <field name="name">Purchase - Important (สำคัญ)</field>
            <field name="category">purchase</field>
            <field name="sla_level">important</field>
            <field name="response_time_hours">16</field>
            <field name="resolve_time_hours">168</field>
        </record>
        
        <record id="sla_purchase_urgent" model="it.sla.policy">
            <field name="name">Purchase - Urgent (เร่งด่วน)</field>
            <field name="category">purchase</field>
            <field name="sla_level">urgent</field>
            <field name="response_time_hours">8</field>
            <field name="resolve_time_hours">72</field>
        </record>
        
        <record id="sla_purchase_critical" model="it.sla.policy">
            <field name="name">Purchase - Critical (วิกฤต)</field>
            <field name="category">purchase</field>
            <field name="sla_level">critical</field>
            <field name="response_time_hours">2</field>
            <field name="resolve_time_hours">24</field>
        </record>
    </data>
</odoo>